test_py_pi_package_eudoro/__init__.py
test_py_pi_package_eudoro/operations.py
test_py_pi_package_eudoro-0.1.1.dist-info/WHEEL
test_py_pi_package_eudoro-0.1.1.dist-info/entry_points.txt
test_py_pi_package_eudoro-0.1.1.dist-info/METADATA
test_py_pi_package_eudoro-0.1.1.dist-info/RECORD
