Metadata-Version: 2.3
Name: test-py-pi-package-eudoro
Version: 0.1.1
Summary: A simple Python package for basic arithmetic operations to test building a python package
Author: Ed Olivares
Author-email: Ed Olivares <34591886+eudoroolivares2016@users.noreply.github.com>
Requires-Dist: requests>=2.32.5
Requires-Python: >=3.10
